Workbook

Sheet Assumptions
A1: CAR DETAILING STARTUP - ASSUMPTIONS & INPUTS
A3: UNIT ECONOMICS | B3: Value
A4: Average Revenue Per Detail (ARPD) | B4: 150
A5: Cost of Materials & Supplies per Job | B5: 25
A6: Labor Cost per Job | B6: 35
A7: Gross Margin per Job | B7: =B4-B5-B6
A8: Gross Margin % | B8: =B7/B4
A10: GROWTH ASSUMPTIONS (MONTHLY) | B10: Value
A11: Month 1: Jobs per Day | B11: 5
A12: Operating Days per Month | B12: 20
A13: Monthly Job Growth Rate | B13: 0.08
A14: Projection Period (Years) | B14: 5
A16: ANNUAL PRICING & VOLUME | B16: Value
A17: Annual Price Increase % | B17: 0.05
A18: Year 2+ Location Expansion (# locations) | B18: 0
A20: OPERATING COSTS (ANNUAL) | B20: Value
A21: Rent (per location, annual) | B21: 24000
A22: Utilities & Insurance (per location) | B22: 6000
A23: Management Salary (Owner) | B23: 50000
A24: Marketing & Customer Acquisition | B24: 12000
A25: Equipment & Supplies (initial + maintenance) | B25: 8000
A27: FINANCING & DISCOUNT RATE | B27: Value
A28: Initial Capital Required | B28: 50000
A29: DCF Discount Rate (WACC) | B29: 0.1
A30: Terminal Growth Rate | B30: 0.03

Sheet Revenue Projections
A1: REVENUE PROJECTIONS
A3: Year | B3: Year 1 | C3: Year 2 | D3: Year 3 | E3: Year 4 | F3: Year 5
A4: # of Locations | B4: 1 | C4: 1 | D4: 1 | E4: 1 | F4: 1
A5: Jobs per Day (per location, YE) | B5: =Assumptions!$B$11*(1+Assumptions!$B$13)^11 | C5: =B5*(1+Assumptions!$B$13)^12 | D5: =C5*(1+Assumptions!$B$13)^12 | E5: =D5*(1+Assumptions!$B$13)^12 | F5: =E5*(1+Assumptions!$B$13)^12
A6: Avg Jobs per Day (during year) | B6: =(Assumptions!$B$11 + B5) / 2 | C6: =(B5 + C5) / 2 | D6: =(C5 + D5) / 2 | E6: =(D5 + E5) / 2 | F6: =(E5 + F5) / 2
A7: Operating Days per Year | B7: =$B$7 | C7: =$B$7 | D7: =$B$7 | E7: =$B$7 | F7: =$B$7
A8: Total Jobs per Year | B8: =B4*B6*B7 | C8: =C4*C6*C7 | D8: =D4*D6*D7 | E8: =E4*E6*E7 | F8: =F4*F6*F7
A9: ARPD | B9: =Assumptions!$B$4 | C9: =B9*(1+Assumptions!$B$17) | D9: =C9*(1+Assumptions!$B$17) | E9: =D9*(1+Assumptions!$B$17) | F9: =E9*(1+Assumptions!$B$17)
A10: Total Revenue | B10: =B8*B9 | C10: =C8*C9 | D10: =D8*D9 | E10: =E8*E9 | F10: =F8*F9

Sheet Operating Expenses
A1: OPERATING EXPENSES
A3: Year | B3: Year 1 | C3: Year 2 | D3: Year 3 | E3: Year 4 | F3: Year 5
A4: COGS - VARIABLE
A5: Materials & Supplies Cost | B5: ='Revenue Projections'!B8*Assumptions!$B$5 | C5: ='Revenue Projections'!C8*Assumptions!$B$5 | D5: ='Revenue Projections'!D8*Assumptions!$B$5 | E5: ='Revenue Projections'!E8*Assumptions!$B$5 | F5: ='Revenue Projections'!F8*Assumptions!$B$5
A6: Labor Cost | B6: ='Revenue Projections'!B8*Assumptions!$B$6 | C6: ='Revenue Projections'!C8*Assumptions!$B$6 | D6: ='Revenue Projections'!D8*Assumptions!$B$6 | E6: ='Revenue Projections'!E8*Assumptions!$B$6 | F6: ='Revenue Projections'!F8*Assumptions!$B$6
A7: Total COGS | B7: =B5+B6 | C7: =C5+C6 | D7: =D5+D6 | E7: =E5+E6 | F7: =F5+F6
A9: FIXED OPERATING EXPENSES
A10: Rent (per location) | B10: ='Revenue Projections'!B4*Assumptions!$B$21 | C10: ='Revenue Projections'!C4*Assumptions!$B$21 | D10: ='Revenue Projections'!D4*Assumptions!$B$21 | E10: ='Revenue Projections'!E4*Assumptions!$B$21 | F10: ='Revenue Projections'!F4*Assumptions!$B$21
A11: Utilities & Insurance | B11: ='Revenue Projections'!B4*Assumptions!$B$22 | C11: ='Revenue Projections'!C4*Assumptions!$B$22 | D11: ='Revenue Projections'!D4*Assumptions!$B$22 | E11: ='Revenue Projections'!E4*Assumptions!$B$22 | F11: ='Revenue Projections'!F4*Assumptions!$B$22
A12: Management Salary | B12: =Assumptions!$B$23 | C12: =Assumptions!$B$23 | D12: =Assumptions!$B$23 | E12: =Assumptions!$B$23 | F12: =Assumptions!$B$23
A13: Marketing & Customer Acquisition | B13: =Assumptions!$B$24 | C13: =Assumptions!$B$24 | D13: =Assumptions!$B$24 | E13: =Assumptions!$B$24 | F13: =Assumptions!$B$24
A14: Equipment & Supplies | B14: =Assumptions!$B$25 | C14: =Assumptions!$B$25 | D14: =Assumptions!$B$25 | E14: =Assumptions!$B$25 | F14: =Assumptions!$B$25
A15: Total Fixed Operating Expenses | B15: =B10+B11+B12+B13+B14 | C15: =C10+C11+C12+C13+C14 | D15: =D10+D11+D12+D13+D14 | E15: =E10+E11+E12+E13+E14 | F15: =F10+F11+F12+F13+F14

Sheet P&L Summary
A1: PROFIT & LOSS SUMMARY
A3: Year | B3: Year 1 | C3: Year 2 | D3: Year 3 | E3: Year 4 | F3: Year 5
A4: Revenue | B4: ='Revenue Projections'!B10 | C4: ='Revenue Projections'!C10 | D4: ='Revenue Projections'!D10 | E4: ='Revenue Projections'!E10 | F4: ='Revenue Projections'!F10
A5: Cost of Goods Sold | B5: ='Operating Expenses'!B7 | C5: ='Operating Expenses'!C7 | D5: ='Operating Expenses'!D7 | E5: ='Operating Expenses'!E7 | F5: ='Operating Expenses'!F7
A6: Gross Profit | B6: =B4-B5 | C6: =C4-C5 | D6: =D4-D5 | E6: =E4-E5 | F6: =F4-F5
A7: Gross Margin % | B7: =B6/B4 | C7: =C6/C4 | D7: =D6/D4 | E7: =E6/E4 | F7: =F6/F4
A9: Operating Expenses | B9: ='Operating Expenses'!B15 | C9: ='Operating Expenses'!C15 | D9: ='Operating Expenses'!D15 | E9: ='Operating Expenses'!E15 | F9: ='Operating Expenses'!F15
A10: EBITDA | B10: =B6-B9 | C10: =C6-C9 | D10: =D6-D9 | E10: =E6-E9 | F10: =F6-F9
A11: EBITDA Margin % | B11: =B10/B4 | C11: =C10/C4 | D11: =D10/D4 | E11: =E10/E4 | F11: =F10/F4

Sheet Valuation
A1: ENTERPRISE VALUATION
A3: DISCOUNTED CASH FLOW (DCF)
A5: Year | B5: 1 | C5: 2 | D5: 3 | E5: 4 | F5: 5
A6: EBITDA | B6: ='P&L Summary'!B10 | C6: ='P&L Summary'!C10 | D6: ='P&L Summary'!D10 | E6: ='P&L Summary'!E10 | F6: ='P&L Summary'!F10
A7: Less: Taxes (25%) | B7: =B6*0.25 | C7: =C6*0.25 | D7: =D6*0.25 | E7: =E6*0.25 | F7: =F6*0.25
A8: NOPAT (Net Operating Profit) | B8: =B6-B7 | C8: =C6-C7 | D8: =D6-D7 | E8: =E6-E7 | F8: =F6-F7
A9: Discount Factor | B9: =1/(1+Assumptions!$B$29)^1 | C9: =1/(1+Assumptions!$B$29)^2 | D9: =1/(1+Assumptions!$B$29)^3 | E9: =1/(1+Assumptions!$B$29)^4 | F9: =1/(1+Assumptions!$B$29)^5
A10: PV of Cash Flows | B10: =B8*B9 | C10: =C8*C9 | D10: =D8*D9 | E10: =E8*E9 | F10: =F8*F9
A12: Sum of PV (5 Years) | B12: =SUM(B10:F10)
A13: Terminal Value (NOPAT Year 5 * 8x EBITDA multiple) | B13: =F8*8
A14: PV of Terminal Value | B14: =B13*F9
A16: ENTERPRISE VALUE (DCF) | B16: =B12+B14
A19: MULTIPLE-BASED VALUATION | B19: Value
A20: Year 5 Revenue | B20: ='P&L Summary'!F4
A21: Revenue Multiple (3.5x) | B21: 3.5
A22: Valuation @ Revenue Multiple | B22: =B20*B21
A24: Year 5 EBITDA | B24: ='P&L Summary'!F10
A25: EBITDA Multiple (6.0x) | B25: 6
A26: Valuation @ EBITDA Multiple | B26: =B24*B25
A28: VALUATION SUMMARY
A29: DCF Valuation | B29: =B16
A30: Revenue Multiple Valuation | B30: =B22
A31: EBITDA Multiple Valuation | B31: =B26
A32: Average Valuation | B32: =AVERAGE(B29:B31)

Sheet Scenario Analysis
A1: SCENARIO ANALYSIS - YEAR 5 PERFORMANCE
A3: Scenario | B3: Monthly Growth | C3: Year 5 Revenue | D3: Year 5 EBITDA | E3: EBITDA Margin
A4: BASE CASE | B4: =Assumptions!$B$13 | C4: ='P&L Summary'!F4 | D4: ='P&L Summary'!F10 | E4: ='P&L Summary'!F11
A5: CONSERVATIVE | B5: 0.05
A6: OPTIMISTIC | B6: 0.12
A8: INSTRUCTIONS:
A9: Update the Monthly Growth rates for Conservative (5%) and Optimistic (12%) scenarios, and the model will recalculate all values in the yellow cells.
